README.rst
setup.py
domain_parser/__init__.py
domain_parser/domain_parser.py
domain_parser.egg-info/PKG-INFO
domain_parser.egg-info/SOURCES.txt
domain_parser.egg-info/dependency_links.txt
domain_parser.egg-info/pbr.json
domain_parser.egg-info/requires.txt
domain_parser.egg-info/top_level.txt
domain_parser.egg-info/version_info.json