Metadata-Version: 1.1
Name: domain-parser
Version: 0.0.5
Summary: Proper domain parser using TLD info from publicsuffix.org
Home-page: http://github.com/jeffknupp/domain-parser/
Author: Jeff Knupp
Author-email: jeff@jeffknupp.com
License: Apache Software License
Platform: any
Classifier: Programming Language :: Python
Classifier: Development Status :: 4 - Beta
Classifier: Natural Language :: English
Classifier: Environment :: Web Environment
Classifier: Intended Audience :: Developers
Classifier: License :: OSI Approved :: Apache Software License
Classifier: Operating System :: OS Independent
Classifier: Topic :: Software Development :: Libraries :: Python Modules
Classifier: Topic :: Internet :: WWW/HTTP :: Dynamic Content
